debugg_ai_sdk/__init__.py
debugg_ai_sdk/_compat.py
debugg_ai_sdk/_init_implementation.py
debugg_ai_sdk/_log_batcher.py
debugg_ai_sdk/_lru_cache.py
debugg_ai_sdk/_queue.py
debugg_ai_sdk/_types.py
debugg_ai_sdk/_werkzeug.py
debugg_ai_sdk/api.py
debugg_ai_sdk/attachments.py
debugg_ai_sdk/client.py
debugg_ai_sdk/consts.py
debugg_ai_sdk/debug.py
debugg_ai_sdk/envelope.py
debugg_ai_sdk/feature_flags.py
debugg_ai_sdk/hub.py
debugg_ai_sdk/logger.py
debugg_ai_sdk/metrics.py
debugg_ai_sdk/monitor.py
debugg_ai_sdk/py.typed
debugg_ai_sdk/scope.py
debugg_ai_sdk/scrubber.py
debugg_ai_sdk/serializer.py
debugg_ai_sdk/session.py
debugg_ai_sdk/sessions.py
debugg_ai_sdk/spotlight.py
debugg_ai_sdk/tracing.py
debugg_ai_sdk/tracing_utils.py
debugg_ai_sdk/transport.py
debugg_ai_sdk/types.py
debugg_ai_sdk/utils.py
debugg_ai_sdk/worker.py
debugg_ai_sdk/ai/__init__.py
debugg_ai_sdk/ai/monitoring.py
debugg_ai_sdk/ai/utils.py
debugg_ai_sdk/crons/__init__.py
debugg_ai_sdk/crons/api.py
debugg_ai_sdk/crons/consts.py
debugg_ai_sdk/crons/decorator.py
debugg_ai_sdk/integrations/__init__.py
debugg_ai_sdk/integrations/_asgi_common.py
debugg_ai_sdk/integrations/_wsgi_common.py
debugg_ai_sdk/integrations/aiohttp.py
debugg_ai_sdk/integrations/anthropic.py
debugg_ai_sdk/integrations/argv.py
debugg_ai_sdk/integrations/ariadne.py
debugg_ai_sdk/integrations/arq.py
debugg_ai_sdk/integrations/asgi.py
debugg_ai_sdk/integrations/asyncio.py
debugg_ai_sdk/integrations/asyncpg.py
debugg_ai_sdk/integrations/atexit.py
debugg_ai_sdk/integrations/aws_lambda.py
debugg_ai_sdk/integrations/beam.py
debugg_ai_sdk/integrations/boto3.py
debugg_ai_sdk/integrations/bottle.py
debugg_ai_sdk/integrations/chalice.py
debugg_ai_sdk/integrations/clickhouse_driver.py
debugg_ai_sdk/integrations/cloud_resource_context.py
debugg_ai_sdk/integrations/cohere.py
debugg_ai_sdk/integrations/dedupe.py
debugg_ai_sdk/integrations/dramatiq.py
debugg_ai_sdk/integrations/excepthook.py
debugg_ai_sdk/integrations/executing.py
debugg_ai_sdk-0.1.13.dist-info/LICENSE
debugg_ai_sdk-0.1.13.dist-info/METADATA
debugg_ai_sdk-0.1.13.dist-info/WHEEL
debugg_ai_sdk-0.1.13.dist-info/top_level.txt
debugg_ai_sdk-0.1.13.dist-info/RECORD
